export_ig/__init__.py
export_ig/color_utils.py
export_ig/export_ig.py
export_ig/shadow_pad.py
export_ig-1.0.3.dist-info/LICENSE
export_ig-1.0.3.dist-info/METADATA
export_ig-1.0.3.dist-info/WHEEL
export_ig-1.0.3.dist-info/entry_points.txt
export_ig-1.0.3.dist-info/top_level.txt
export_ig-1.0.3.dist-info/RECORD
