Metadata-Version: 2.1
Name: export-ig
Version: 1.0.3
Summary: Package for processing images for Instagram upload.
Home-page: https://github.com/syncdoth/export_ig
Author: Sehyun Choi
Author-email: choisehyun98@gmail.com
License: Apache
Classifier: Programming Language :: Python :: 3
Requires-Python: >=3.8
License-File: LICENSE
Requires-Dist: Pillow
Requires-Dist: joblib (>=1.2.0)
Requires-Dist: simple-parsing
